[
    {
        "status": "Live",
        "type": "Improvements",
        "content": "Fixes voxelization of invalid parts and meshes."
    },
    {
        "status": "Live",
        "type": "Improvements",
        "content": "Luau user-defined type functions now support Luau thread and buffer primitive types"
    },
    {
        "status": "Live",
        "type": "Improvements",
        "content": "Fixed false positive Luau type errors when using 'vector' type properties and operators."
    },
    {
        "status": "Live",
        "type": "Improvements",
        "content": "Instance picker is now more consistent about cancelling itself when clicking out of the viewport."
    },
    {
        "status": "Live",
        "type": "Fixes",
        "content": "When Script Sandboxing is used, modules required using an asset ID will execute in the sandbox context of the caller."
    },
    {
        "status": "Live",
        "type": "Fixes",
        "content": "EditableMesh now works better with perfect planes"
    },
    {
        "status": "Live",
        "type": "Fixes",
        "content": "Added support for rbxthumb ContentIds in AssetService:CreateEditableImageAsync"
    },
    {
        "status": "Live",
        "type": "Fixes",
        "content": "Updates <code>Class.AudioEcho</code> to use less memory"
    }
]